arcanum/__init__.py
arcanum/__main__.py
arcanum-0.1.0a0.dist-info/METADATA
arcanum-0.1.0a0.dist-info/WHEEL
arcanum-0.1.0a0.dist-info/entry_points.txt
arcanum-0.1.0a0.dist-info/licenses/LICENSE.txt
arcanum-0.1.0a0.dist-info/RECORD
